boring_math/probability_distributions/__init__.py
boring_math/probability_distributions/datasets.py
boring_math/probability_distributions/distribution.py
boring_math/probability_distributions/py.typed
boring_math/probability_distributions/distributions/__init__.py
boring_math/probability_distributions/distributions/binomial.py
boring_math/probability_distributions/distributions/normal.py
boring_math/probability_distributions/distributions/py.typed
boring_math/probability_distributions/distributions/uniform.py
boring_math_probability_distributions-0.8.1.dist-info/licenses/LICENSE
boring_math_probability_distributions-0.8.1.dist-info/WHEEL
boring_math_probability_distributions-0.8.1.dist-info/METADATA
boring_math_probability_distributions-0.8.1.dist-info/RECORD
