Metadata-Version: 2.4
Name: boring-math-probability-distributions
Version: 0.8.1
Summary: Visualize probability distributions
Keywords: distribution,probability distributions,sample data
Author-email: "Geoffrey R. Scheller" <geoffrey@scheller.com>
Requires-Python: >=3.13
Classifier: Development Status :: 2 - Pre-Alpha
Classifier: Framework :: Pytest
Classifier: Intended Audience :: Education
Classifier: License :: OSI Approved :: Apache Software License
Classifier: Operating System :: OS Independent
Classifier: Programming Language :: Python :: 3.13
Classifier: Typing :: Typed
License-File: LICENSE
Requires-Dist: matplotlib >= 3.10.1
Requires-Dist: pythonic-fp.fptools >= 5.1.1
Requires-Dist: pytest>=8.4.1 ; extra == "test"
Project-URL: Changelog, https://github.com/grscheller/boring-math-probability-distributions/blob/main/CHANGELOG.rst
Project-URL: Documentation, https://grscheller.github.io/boring-math/probability-distributions/development/build/html/
Project-URL: Homepage, https://grscheller.github.io/boring-math/homepage/build/html/
Project-URL: Source, https://github.com/grscheller/boring-math-probability-distributions
Provides-Extra: test
